{
    "os": "Linux-5.15.0-78-generic-x86_64-with-glibc2.31",
    "python": "3.10.12",
    "heartbeatAt": "2023-07-28T13:56:34.294702",
    "startedAt": "2023-07-28T13:56:33.849958",
    "docker": null,
    "cuda": null,
    "args": null,
    "state": "running",
    "program": "<python with no main file>",
    "git": {
        "remote": "https://github.com/paulcode123/Bidirectional-VAE.git",
        "commit": "c051750adccbd555318f557724e061cd7dc01171"
    },
    "email": "anant.v.rai@gmail.com",
    "root": "/home/robot-lab/Documents/Paul",
    "host": "lambda-dual-eureka",
    "username": "robot-lab",
    "executable": "/home/robot-lab/anaconda3/envs/BVAE/bin/python",
    "cpu_count": 12,
    "cpu_count_logical": 24,
    "cpu_freq": {
        "current": 2753.2584583333337,
        "min": 2200.0,
        "max": 3800.0
    },
    "cpu_freq_per_core": [
        {
            "current": 2200.0,
            "min": 2200.0,
            "max": 3800.0
        },
        {
            "current": 3800.0,
            "min": 2200.0,
            "max": 3800.0
        },
        {
            "current": 2200.0,
            "min": 2200.0,
            "max": 3800.0
        },
        {
            "current": 4153.59,
            "min": 2200.0,
            "max": 3800.0
        },
        {
            "current": 2200.0,
            "min": 2200.0,
            "max": 3800.0
        },
        {
            "current": 2200.0,
            "min": 2200.0,
            "max": 3800.0
        },
        {
            "current": 2200.0,
            "min": 2200.0,
            "max": 3800.0
        },
        {
            "current": 4152.376,
            "min": 2200.0,
            "max": 3800.0
        },
        {
            "current": 4125.482,
            "min": 2200.0,
            "max": 3800.0
        },
        {
            "current": 4151.241,
            "min": 2200.0,
            "max": 3800.0
        },
        {
            "current": 2200.0,
            "min": 2200.0,
            "max": 3800.0
        },
        {
            "current": 4154.309,
            "min": 2200.0,
            "max": 3800.0
        },
        {
            "current": 2200.0,
            "min": 2200.0,
            "max": 3800.0
        },
        {
            "current": 2200.0,
            "min": 2200.0,
            "max": 3800.0
        },
        {
            "current": 2200.0,
            "min": 2200.0,
            "max": 3800.0
        },
        {
            "current": 2200.0,
            "min": 2200.0,
            "max": 3800.0
        },
        {
            "current": 2200.0,
            "min": 2200.0,
            "max": 3800.0
        },
        {
            "current": 2800.0,
            "min": 2200.0,
            "max": 3800.0
        },
        {
            "current": 2200.0,
            "min": 2200.0,
            "max": 3800.0
        },
        {
            "current": 3800.0,
            "min": 2200.0,
            "max": 3800.0
        },
        {
            "current": 2200.0,
            "min": 2200.0,
            "max": 3800.0
        },
        {
            "current": 3800.0,
            "min": 2200.0,
            "max": 3800.0
        },
        {
            "current": 2200.0,
            "min": 2200.0,
            "max": 3800.0
        },
        {
            "current": 2200.0,
            "min": 2200.0,
            "max": 3800.0
        }
    ],
    "disk": {
        "total": 915.3232879638672,
        "used": 838.5429954528809
    },
    "gpu": "NVIDIA GeForce RTX 3090",
    "gpu_count": 2,
    "gpu_devices": [
        {
            "name": "NVIDIA GeForce RTX 3090",
            "memory_total": 25769803776
        },
        {
            "name": "NVIDIA GeForce RTX 3090",
            "memory_total": 25769803776
        }
    ],
    "memory": {
        "total": 62.715545654296875
    }
}
